azure/mgmt/authorization/__init__.py
azure/mgmt/authorization/_authorization_management_client.py
azure/mgmt/authorization/_configuration.py
azure/mgmt/authorization/_serialization.py
azure/mgmt/authorization/_version.py
azure/mgmt/authorization/models.py
azure/mgmt/authorization/py.typed
azure/mgmt/authorization/aio/__init__.py
azure/mgmt/authorization/aio/_authorization_management_client.py
azure/mgmt/authorization/aio/_configuration.py
azure/mgmt/authorization/v2015_06_01/__init__.py
azure/mgmt/authorization/v2015_06_01/_authorization_management_client.py
azure/mgmt/authorization/v2015_06_01/_configuration.py
azure/mgmt/authorization/v2015_06_01/_patch.py
azure/mgmt/authorization/v2015_06_01/_vendor.py
azure/mgmt/authorization/v2015_06_01/_version.py
azure/mgmt/authorization/v2015_06_01/aio/__init__.py
azure/mgmt/authorization/v2015_06_01/aio/_authorization_management_client.py
azure/mgmt/authorization/v2015_06_01/aio/_configuration.py
azure/mgmt/authorization/v2015_06_01/aio/_patch.py
azure/mgmt/authorization/v2015_06_01/aio/operations/__init__.py
azure/mgmt/authorization/v2015_06_01/aio/operations/_classic_administrators_operations.py
azure/mgmt/authorization/v2015_06_01/aio/operations/_patch.py
azure/mgmt/authorization/v2015_06_01/models/__init__.py
azure/mgmt/authorization/v2015_06_01/models/_models_py3.py
azure/mgmt/authorization/v2015_06_01/models/_patch.py
azure/mgmt/authorization/v2015_06_01/operations/__init__.py
azure/mgmt/authorization/v2015_06_01/operations/_classic_administrators_operations.py
azure/mgmt/authorization/v2015_06_01/operations/_patch.py
azure/mgmt/authorization/v2015_07_01/__init__.py
azure/mgmt/authorization/v2015_07_01/_authorization_management_client.py
azure/mgmt/authorization/v2015_07_01/_configuration.py
azure/mgmt/authorization/v2015_07_01/_patch.py
azure/mgmt/authorization/v2015_07_01/_vendor.py
azure/mgmt/authorization/v2015_07_01/_version.py
azure/mgmt/authorization/v2015_07_01/aio/__init__.py
azure_mgmt_authorization-3.0.0.dist-info/LICENSE
azure_mgmt_authorization-3.0.0.dist-info/METADATA
azure_mgmt_authorization-3.0.0.dist-info/WHEEL
azure_mgmt_authorization-3.0.0.dist-info/top_level.txt
azure_mgmt_authorization-3.0.0.dist-info/RECORD
